<DOMSymbolItem xmlns:xsi="http://www.w3.org/2001/XMLSchema-instance" xmlns="http://ns.adobe.com/xfl/2008/" name="_Tweens/Tween 49" itemID="5458ce30-000002c3" symbolType="graphic" lastModified="1415106172">
  <timeline>
    <DOMTimeline name="Tween 49">
      <layers>
        <DOMLayer name="Layer 1" color="#4FFF4F" current="true" isSelected="true">
          <frames>
            <DOMFrame index="0" keyMode="9728">
              <elements>
                <DOMShape>
                  <fills>
                    <FillStyle index="1">
                      <SolidColor color="#00CCCC" alpha="0.976470588235294"/>
                    </FillStyle>
                  </fills>
                  <edges>
                    <Edge fillStyle0="1" edges="!296 -94|277 -94!277 -94[261 -94 250 -91!250 -91[239 -88 239 -84!239 -84|239 85!239 85[239 89 250 92!250 92[261 95 277 95!277 95|296 95!296 95[312 95 323 92!323 92[334 89 334 85!334 85|334 -84!334 -84[334 -88 323 -91!323 -91[312 -94 296
 -94!774 -84|774 85!774 85[774 89 785 92!785 92[796 95 812 95!812 95|831 95!831 95[847 95 858 92!858 92[869 89 869 85!869 85|869 -84!869 -84[869 -88 858 -91!858 -91[847 -94 831 -94!831 -94|812 -94!812 -94[796 -94 785 -91!785 -91[774 -88
 774 -84!1723 -91[1712 -94 1696 -94!1696 -94|1677 -94!1677 -94[1661 -94 1650 -91!1650 -91[1639 -88 1639 -84!1639 -84|1639 85!1639 85[1639 89 1650 92!1650 92[1661 95 1677 95!1677 95|1696 95!1696 95[1712 95 1723 92!1723 92[1734 89 1734
 85!1734 85|1734 -84!1734 -84[1734 -88 1723 -91!2547 -94[2531 -94 2520 -91!2520 -91[2509 -88 2509 -84!2509 -84|2509 85!2509 85[2509 89 2520 92!2520 92[2531 95 2547 95!2547 95|2566 95!2566 95[2582 95 2593 92!2593 92[2604 89 2604 85!2604
 85|2604 -84!2604 -84[2604 -88 2593 -91!2593 -91[2582 -94 2566 -94!2566 -94|2547 -94!4570 -91[4559 -88 4559 -84!4559 -84|4559 85!4559 85[4559 89 4570 92!4570 92[4581 95 4597 95!4597 95|4616 95!4616 95[4632 95 4643 92!4643 92[4654 89 4654
 85!4654 85|4654 -84!4654 -84[4654 -88 4643 -91!4643 -91[4632 -94 4616 -94!4616 -94|4597 -94!4597 -94[4581 -94 4570 -91!6289 -95|6270 -95!6270 -95[6254 -95 6243 -92!6243 -92[6232 -89 6232 -84!6232 -84|6232 84!6232 84[6232 89 6243 92!6243
 92[6254 95 6270 95!6270 95|6289 95!6289 95[6305 95 6316 92!6316 92[6327 89 6327 84!6327 84|6327 -84!6327 -84[6327 -89 6316 -92!6316 -92[6305 -95 6289 -95!-6269 -94|-6288 -94!-6288 -94[-6304 -94 -6315 -91!-6315 -91[-6326 -88 -6326 -84
!-6326 -84|-6326 85!-6326 85[-6326 89 -6315 92!-6315 92[-6304 95 -6288 95!-6288 95|-6269 95!-6269 95[-6253 95 -6242 92!-6242 92[-6231 89 -6231 85!-6231 85|-6231 -84!-6231 -84[-6231 -88 -6242 -91!-6242 -91[-6253 -94 -6269 -94!-5254 -94
|-5273 -94!-5273 -94[-5289 -94 -5300 -91!-5300 -91[-5311 -88 -5311 -84!-5311 -84|-5311 85!-5311 85[-5311 89 -5300 92!-5300 92[-5289 95 -5273 95!-5273 95|-5254 95!-5254 95[-5238 95 -5227 92!-5227 92[-5216 89 -5216 85!-5216 85|-5216 -84
!-5216 -84[-5216 -88 -5227 -91!-5227 -91[-5238 -94 -5254 -94!-3636 -82|-3636 86!-3636 86[-3636 90 -3625 93!-3625 93[-3614 96 -3598 96!-3598 96|-3579 96!-3579 96[-3563 96 -3552 93!-3552 93[-3541 90 -3541 86!-3541 86|-3541 -82!-3541 -82
[-3541 -87 -3552 -90!-3552 -90[-3563 -93 -3579 -93!-3579 -93|-3598 -93!-3598 -93[-3614 -93 -3625 -90!-3625 -90[-3636 -87 -3636 -82!-3326 -84|-3326 85!-3326 85[-3326 89 -3315 92!-3315 92[-3304 95 -3288 95!-3288 95|-3269 95!-3269 95[-3253
 95 -3242 92!-3242 92[-3231 89 -3231 85!-3231 85|-3231 -84!-3231 -84[-3231 -88 -3242 -91!-3242 -91[-3253 -94 -3269 -94!-3269 -94|-3288 -94!-3288 -94[-3304 -94 -3315 -91!-3315 -91[-3326 -88 -3326 -84"/>
                    <Edge cubics="!-3598 96(-3598,96;-3598,96 -3579,96 -3579,96q-3598 96 -3579 96);"/>
                    <Edge cubics="!-6288 -94(;-6299,-94 -6308,-93 -6315,-91q-6288 -94Q-6304 -94q-6315 -91);"/>
                    <Edge cubics="!-6269 -94(;-6269,-94 -6288,-94 -6288,-94q-6269 -94 -6288 -94);"/>
                    <Edge cubics="!-6242 -91(-6242,-91;-6249,-93 -6258,-94 -6269,-94q-6242 -91Q-6253 -94q-6269 -94);"/>
                    <Edge cubics="!-6231 -84(;-6231,-87 -6235,-89 -6242,-91q-6231 -84Q-6231 -88q-6242 -91);"/>
                    <Edge cubics="!-6315 -91(;-6322,-89 -6326,-87 -6326,-84q-6315 -91Q-6326 -88q-6326 -84);"/>
                    <Edge cubics="!-6242 92(;-6235,90 -6231,88 -6231,85q-6242 92Q-6231 89q-6231 85);"/>
                    <Edge cubics="!-6269 95(;-6258,95 -6249,94 -6242,92q-6269 95Q-6253 95q-6242 92);"/>
                    <Edge cubics="!-6288 95(;-6288,95 -6269,95 -6269,95q-6288 95 -6269 95);"/>
                    <Edge cubics="!-6315 92(;-6308,94 -6299,95 -6288,95q-6315 92Q-6304 95q-6288 95);"/>
                    <Edge cubics="!-6326 85(;-6326,88 -6322,90 -6315,92q-6326 85Q-6326 89q-6315 92);"/>
                    <Edge cubics="!-6231 85(;-6231,85 -6231,-84 -6231,-84q-6231 85 -6231 -84);"/>
                    <Edge cubics="!-6326 -84(;-6326,-84 -6326,85 -6326,85q-6326 -84 -6326 85);"/>
                    <Edge cubics="!-5273 -94(-5273,-94;-5284,-94 -5293,-93 -5300,-91q-5273 -94Q-5289 -94q-5300 -91);"/>
                    <Edge cubics="!-5254 -94(-5254,-94;-5254,-94 -5273,-94 -5273,-94q-5254 -94 -5273 -94);"/>
                    <Edge cubics="!-5227 -91(;-5234,-93 -5243,-94 -5254,-94q-5227 -91Q-5238 -94q-5254 -94);"/>
                    <Edge cubics="!-5216 -84(-5216,-84;-5216,-87 -5220,-89 -5227,-91q-5216 -84Q-5216 -88q-5227 -91)-5227,-91;"/>
                    <Edge cubics="!-5300 -91(;-5307,-89 -5311,-87 -5311,-84q-5300 -91Q-5311 -88q-5311 -84);"/>
                    <Edge cubics="!-5227 92(;-5220,90 -5216,88 -5216,85q-5227 92Q-5216 89q-5216 85);"/>
                    <Edge cubics="!-5254 95(;-5243,95 -5234,94 -5227,92q-5254 95Q-5238 95q-5227 92);"/>
                    <Edge cubics="!-5273 95(;-5273,95 -5254,95 -5254,95q-5273 95 -5254 95);"/>
                    <Edge cubics="!-5300 92(;-5293,94 -5284,95 -5273,95q-5300 92Q-5289 95q-5273 95);"/>
                    <Edge cubics="!-5311 85(;-5311,88 -5307,90 -5300,92q-5311 85Q-5311 89q-5300 92);"/>
                    <Edge cubics="!-5216 85(;-5216,85 -5216,-84 -5216,-84q-5216 85 -5216 -84);"/>
                    <Edge cubics="!-5311 -84(;-5311,-84 -5311,85 -5311,85q-5311 -84 -5311 85);"/>
                    <Edge cubics="!-3598 -93(-3598,-93;-3609,-93 -3618,-92 -3625,-90q-3598 -93Q-3614 -93q-3625 -90);"/>
                    <Edge cubics="!-3579 -93(-3579,-93;-3579,-93 -3598,-93 -3598,-93q-3579 -93 -3598 -93);"/>
                    <Edge cubics="!-3552 -90(-3552,-90;-3559,-92 -3568,-93 -3579,-93q-3552 -90Q-3563 -93q-3579 -93);"/>
                    <Edge cubics="!-3541 -82(;-3541,-85 -3545,-88 -3552,-90q-3541 -82Q-3541 -87q-3552 -90);"/>
                    <Edge cubics="!-3625 -90(;-3632,-88 -3636,-85 -3636,-82q-3625 -90Q-3636 -87q-3636 -82);"/>
                    <Edge cubics="!-3552 93(;-3545,91 -3541,89 -3541,86q-3552 93Q-3541 90q-3541 86);"/>
                    <Edge cubics="!-3579 96(;-3568,96 -3559,95 -3552,93q-3579 96Q-3563 96q-3552 93);"/>
                    <Edge cubics="!-3625 93(-3625,93;-3618,95 -3609,96 -3598,96q-3625 93Q-3614 96q-3598 96);"/>
                    <Edge cubics="!-3636 86(;-3636,89 -3632,91 -3625,93q-3636 86Q-3636 90q-3625 93);"/>
                    <Edge cubics="!-3541 86(-3541,86;-3541,86 -3541,-82 -3541,-82q-3541 86 -3541 -82);"/>
                    <Edge cubics="!-3636 -82(-3636,-82;-3636,-82 -3636,86 -3636,86q-3636 -82 -3636 86);"/>
                    <Edge cubics="!-3315 -91(;-3322,-89 -3326,-87 -3326,-84q-3315 -91Q-3326 -88q-3326 -84);"/>
                    <Edge cubics="!-3288 -94(-3288,-94;-3299,-94 -3308,-93 -3315,-91q-3288 -94Q-3304 -94q-3315 -91)-3315,-91;"/>
                    <Edge cubics="!-3269 -94(;-3269,-94 -3288,-94 -3288,-94q-3269 -94 -3288 -94);"/>
                    <Edge cubics="!-3242 -91(;-3249,-93 -3258,-94 -3269,-94q-3242 -91Q-3253 -94q-3269 -94);"/>
                    <Edge cubics="!-3231 -84(;-3231,-87 -3235,-89 -3242,-91q-3231 -84Q-3231 -88q-3242 -91);"/>
                    <Edge cubics="!-3242 92(-3242,92;-3235,90 -3231,88 -3231,85q-3242 92Q-3231 89q-3231 85);"/>
                    <Edge cubics="!-3269 95(;-3258,95 -3249,94 -3242,92q-3269 95Q-3253 95q-3242 92);"/>
                    <Edge cubics="!-3288 95(;-3288,95 -3269,95 -3269,95q-3288 95 -3269 95);"/>
                    <Edge cubics="!-3315 92(;-3308,94 -3299,95 -3288,95q-3315 92Q-3304 95q-3288 95);"/>
                    <Edge cubics="!-3326 85(;-3326,88 -3322,90 -3315,92q-3326 85Q-3326 89q-3315 92);"/>
                    <Edge cubics="!-3231 85(-3231,85;-3231,85 -3231,-84 -3231,-84q-3231 85 -3231 -84);"/>
                    <Edge cubics="!-3326 -84(-3326,-84;-3326,-84 -3326,85 -3326,85q-3326 -84 -3326 85);"/>
                    <Edge cubics="!-500 -91(-500,-91;-507,-89 -511,-87 -511,-84q-500 -91Q-511 -88q-511 -84);"/>
                    <Edge cubics="!-454 -94(;-454,-94 -473,-94 -473,-94q-454 -94 -473 -94);"/>
                    <Edge cubics="!-427 -91(-427,-91;-434,-93 -443,-94 -454,-94q-427 -91Q-438 -94q-454 -94)-454,-94;"/>
                    <Edge cubics="!-416 -84(;-416,-87 -420,-89 -427,-91q-416 -84Q-416 -88q-427 -91);"/>
                    <Edge cubics="!-473 -94(-473,-94;-484,-94 -493,-93 -500,-91q-473 -94Q-489 -94q-500 -91);"/>
                    <Edge cubics="!-511 85(;-511,88 -507,90 -500,92q-511 85Q-511 89q-500 92);"/>
                    <Edge cubics="!-427 92(-427,92;-420,90 -416,88 -416,85q-427 92Q-416 89q-416 85)-416,85;"/>
                    <Edge cubics="!-454 95(;-443,95 -434,94 -427,92q-454 95Q-438 95q-427 92);"/>
                    <Edge cubics="!-473 95(-473,95;-473,95 -454,95 -454,95q-473 95 -454 95);"/>
                    <Edge cubics="!-500 92(-500,92;-493,94 -484,95 -473,95q-500 92Q-489 95q-473 95);"/>
                    <Edge cubics="!-416 85(;-416,85 -416,-84 -416,-84q-416 85 -416 -84);"/>
                    <Edge cubics="!-511 -84(;-511,-84 -511,85 -511,85q-511 -84 -511 85);"/>
                    <Edge cubics="!277 -94(;266,-94 257,-93 250,-91q277 -94Q261 -94q250 -91);"/>
                    <Edge cubics="!296 -94(;296,-94 277,-94 277,-94q296 -94 277 -94);"/>
                    <Edge cubics="!323 -91(323,-91;316,-93 307,-94 296,-94q323 -91Q312 -94q296 -94)296,-94;"/>
                    <Edge cubics="!334 -84(;334,-87 330,-89 323,-91q334 -84Q334 -88q323 -91);"/>
                    <Edge cubics="!250 -91(250,-91;243,-89 239,-87 239,-84q250 -91Q239 -88q239 -84);"/>
                    <Edge cubics="!323 92(323,92;330,90 334,88 334,85q323 92Q334 89q334 85);"/>
                    <Edge cubics="!296 95(296,95;307,95 316,94 323,92q296 95Q312 95q323 92);"/>
                    <Edge cubics="!277 95(277,95;277,95 296,95 296,95q277 95 296 95);"/>
                    <Edge cubics="!250 92(;257,94 266,95 277,95q250 92Q261 95q277 95);"/>
                    <Edge cubics="!239 85(;239,88 243,90 250,92q239 85Q239 89q250 92);"/>
                    <Edge cubics="!334 85(;334,85 334,-84 334,-84q334 85 334 -84);"/>
                    <Edge cubics="!239 -84(239,-84;239,-84 239,85 239,85q239 -84 239 85)239,85;"/>
                    <Edge cubics="!858 -91(;851,-93 842,-94 831,-94q858 -91Q847 -94q831 -94);"/>
                    <Edge cubics="!785 -91(;778,-89 774,-87 774,-84q785 -91Q774 -88q774 -84);"/>
                    <Edge cubics="!812 -94(812,-94;801,-94 792,-93 785,-91q812 -94Q796 -94q785 -91);"/>
                    <Edge cubics="!831 -94(831,-94;831,-94 812,-94 812,-94q831 -94 812 -94);"/>
                    <Edge cubics="!869 -84(;869,-87 865,-89 858,-91q869 -84Q869 -88q858 -91);"/>
                    <Edge cubics="!831 95(;842,95 851,94 858,92q831 95Q847 95q858 92);"/>
                    <Edge cubics="!858 92(;865,90 869,88 869,85q858 92Q869 89q869 85);"/>
                    <Edge cubics="!812 95(812,95;812,95 831,95 831,95q812 95 831 95);"/>
                    <Edge cubics="!785 92(;792,94 801,95 812,95q785 92Q796 95q812 95);"/>
                    <Edge cubics="!774 85(;774,88 778,90 785,92q774 85Q774 89q785 92);"/>
                    <Edge cubics="!774 -84(;774,-84 774,85 774,85q774 -84 774 85);"/>
                    <Edge cubics="!869 85(;869,85 869,-84 869,-84q869 85 869 -84);"/>
                    <Edge cubics="!1650 -91(;1643,-89 1639,-87 1639,-84q1650 -91Q1639 -88q1639 -84);"/>
                    <Edge cubics="!1677 -94(;1666,-94 1657,-93 1650,-91q1677 -94Q1661 -94q1650 -91);"/>
                    <Edge cubics="!1696 -94(;1696,-94 1677,-94 1677,-94q1696 -94 1677 -94);"/>
                    <Edge cubics="!1723 -91(;1716,-93 1707,-94 1696,-94q1723 -91Q1712 -94q1696 -94);"/>
                    <Edge cubics="!1734 -84(;1734,-87 1730,-89 1723,-91q1734 -84Q1734 -88q1723 -91);"/>
                    <Edge cubics="!1723 92(;1730,90 1734,88 1734,85q1723 92Q1734 89q1734 85);"/>
                    <Edge cubics="!1696 95(;1707,95 1716,94 1723,92q1696 95Q1712 95q1723 92);"/>
                    <Edge cubics="!1677 95(;1677,95 1696,95 1696,95q1677 95 1696 95);"/>
                    <Edge cubics="!1650 92(;1657,94 1666,95 1677,95q1650 92Q1661 95q1677 95);"/>
                    <Edge cubics="!1639 85(;1639,88 1643,90 1650,92q1639 85Q1639 89q1650 92);"/>
                    <Edge cubics="!1734 85(1734,85;1734,85 1734,-84 1734,-84q1734 85 1734 -84)1734,-84;"/>
                    <Edge cubics="!1639 -84(1639,-84;1639,-84 1639,85 1639,85q1639 -84 1639 85);"/>
                    <Edge cubics="!2520 -91(;2513,-89 2509,-87 2509,-84q2520 -91Q2509 -88q2509 -84);"/>
                    <Edge cubics="!2547 -94(;2536,-94 2527,-93 2520,-91q2547 -94Q2531 -94q2520 -91);"/>
                    <Edge cubics="!2566 -94(;2566,-94 2547,-94 2547,-94q2566 -94 2547 -94);"/>
                    <Edge cubics="!2593 -91(2593,-91;2586,-93 2577,-94 2566,-94q2593 -91Q2582 -94q2566 -94);"/>
                    <Edge cubics="!2604 -84(2604,-84;2604,-87 2600,-89 2593,-91q2604 -84Q2604 -88q2593 -91);"/>
                    <Edge cubics="!2593 92(2593,92;2600,90 2604,88 2604,85q2593 92Q2604 89q2604 85);"/>
                    <Edge cubics="!2566 95(2566,95;2577,95 2586,94 2593,92q2566 95Q2582 95q2593 92);"/>
                    <Edge cubics="!2547 95(;2547,95 2566,95 2566,95q2547 95 2566 95);"/>
                    <Edge cubics="!2520 92(2520,92;2527,94 2536,95 2547,95q2520 92Q2531 95q2547 95)2547,95;"/>
                    <Edge cubics="!2509 85(;2509,88 2513,90 2520,92q2509 85Q2509 89q2520 92);"/>
                    <Edge cubics="!2604 85(;2604,85 2604,-84 2604,-84q2604 85 2604 -84);"/>
                    <Edge cubics="!2509 -84(;2509,-84 2509,85 2509,85q2509 -84 2509 85);"/>
                    <Edge cubics="!4570 -91(;4563,-89 4559,-87 4559,-84q4570 -91Q4559 -88q4559 -84);"/>
                    <Edge cubics="!4597 -94(;4586,-94 4577,-93 4570,-91q4597 -94Q4581 -94q4570 -91);"/>
                    <Edge cubics="!4616 -94(;4616,-94 4597,-94 4597,-94q4616 -94 4597 -94);"/>
                    <Edge cubics="!4643 -91(4643,-91;4636,-93 4627,-94 4616,-94q4643 -91Q4632 -94q4616 -94);"/>
                    <Edge cubics="!4654 -84(;4654,-87 4650,-89 4643,-91q4654 -84Q4654 -88q4643 -91);"/>
                    <Edge cubics="!4643 92(;4650,90 4654,88 4654,85q4643 92Q4654 89q4654 85);"/>
                    <Edge cubics="!4616 95(;4627,95 4636,94 4643,92q4616 95Q4632 95q4643 92);"/>
                    <Edge cubics="!4597 95(;4597,95 4616,95 4616,95q4597 95 4616 95);"/>
                    <Edge cubics="!4570 92(4570,92;4577,94 4586,95 4597,95q4570 92Q4581 95q4597 95);"/>
                    <Edge cubics="!4559 85(4559,85;4559,88 4563,90 4570,92q4559 85Q4559 89q4570 92);"/>
                    <Edge cubics="!4654 85(4654,85;4654,85 4654,-84 4654,-84q4654 85 4654 -84);"/>
                    <Edge cubics="!4559 -84(4559,-84;4559,-84 4559,85 4559,85q4559 -84 4559 85);"/>
                    <Edge cubics="!6243 -92(6243,-92;6236,-90 6232,-87 6232,-84q6243 -92Q6232 -89q6232 -84);"/>
                    <Edge cubics="!6270 -95(6270,-95;6259,-95 6250,-94 6243,-92q6270 -95Q6254 -95q6243 -92);"/>
                    <Edge cubics="!6289 -95(;6289,-95 6270,-95 6270,-95q6289 -95 6270 -95);"/>
                    <Edge cubics="!6316 -92(;6309,-94 6300,-95 6289,-95q6316 -92Q6305 -95q6289 -95);"/>
                    <Edge cubics="!6327 -84(;6327,-87 6323,-90 6316,-92q6327 -84Q6327 -89q6316 -92);"/>
                    <Edge cubics="!6316 92(;6323,90 6327,87 6327,84q6316 92Q6327 89q6327 84);"/>
                    <Edge cubics="!6289 95(6289,95;6300,95 6309,94 6316,92q6289 95Q6305 95q6316 92);"/>
                    <Edge cubics="!6270 95(6270,95;6270,95 6289,95 6289,95q6270 95 6289 95);"/>
                    <Edge cubics="!6243 92(6243,92;6250,94 6259,95 6270,95q6243 92Q6254 95q6270 95);"/>
                    <Edge cubics="!6232 84(6232,84;6232,87 6236,90 6243,92q6232 84Q6232 89q6243 92);"/>
                    <Edge cubics="!6327 84(;6327,84 6327,-84 6327,-84q6327 84 6327 -84);"/>
                    <Edge cubics="!6232 -84(6232,-84;6232,-84 6232,84 6232,84q6232 -84 6232 84)6232,84;"/>
                  </edges>
                </DOMShape>
              </elements>
            </DOMFrame>
          </frames>
        </DOMLayer>
      </layers>
    </DOMTimeline>
  </timeline>
</DOMSymbolItem>